{
  "generated_on": "2026-04-30",
  "summary": {
    "total_opportunities": 2600,
    "total_pipeline_value": 246709900.0,
    "open_weighted_pipeline": 43297795.0,
    "won_revenue": 57590400.0,
    "win_rate_pct": 34.5,
    "avg_sales_cycle_days": 72.1
  },
  "tables": {
    "funnel_by_stage": [
      {
        "stage": "Prospecting",
        "opportunities": 37,
        "pipeline_value": 6061700.0,
        "weighted_pipeline": 606170.0
      },
      {
        "stage": "Discovery",
        "opportunities": 47,
        "pipeline_value": 7420100.0,
        "weighted_pipeline": 1855025.0
      },
      {
        "stage": "Proposal",
        "opportunities": 308,
        "pipeline_value": 30451200.0,
        "weighted_pipeline": 15225600.0
      },
      {
        "stage": "Negotiation",
        "opportunities": 339,
        "pipeline_value": 34148000.0,
        "weighted_pipeline": 25611000.0
      },
      {
        "stage": "Closed Won",
        "opportunities": 645,
        "pipeline_value": 57590400.0,
        "weighted_pipeline": 57590400.0
      },
      {
        "stage": "Closed Lost",
        "opportunities": 1224,
        "pipeline_value": 111038500.0,
        "weighted_pipeline": 0.0
      }
    ],
    "rep_performance": [
      {
        "sales_rep": "Liam Davis",
        "total_opportunities": 347,
        "won_deals": 76,
        "win_rate_pct": 30.9,
        "won_revenue": 15002100.0,
        "avg_days_to_close": 108.8,
        "open_weighted_pipeline": 11016230.0
      },
      {
        "sales_rep": "Priya Shah",
        "total_opportunities": 323,
        "won_deals": 62,
        "win_rate_pct": 31.0,
        "won_revenue": 12958100.0,
        "avg_days_to_close": 105.0,
        "open_weighted_pipeline": 15000300.0
      },
      {
        "sales_rep": "Maya Patel",
        "total_opportunities": 331,
        "won_deals": 91,
        "win_rate_pct": 37.9,
        "won_revenue": 8285700.0,
        "avg_days_to_close": 80.9,
        "open_weighted_pipeline": 5061715.0
      },
      {
        "sales_rep": "Avery Chen",
        "total_opportunities": 310,
        "won_deals": 84,
        "win_rate_pct": 36.5,
        "won_revenue": 7626100.0,
        "avg_days_to_close": 82.2,
        "open_weighted_pipeline": 4041020.0
      },
      {
        "sales_rep": "Jordan Smith",
        "total_opportunities": 343,
        "won_deals": 101,
        "win_rate_pct": 39.8,
        "won_revenue": 4333400.0,
        "avg_days_to_close": 56.8,
        "open_weighted_pipeline": 2336295.0
      },
      {
        "sales_rep": "Sofia Garcia",
        "total_opportunities": 318,
        "won_deals": 93,
        "win_rate_pct": 41.2,
        "won_revenue": 4239300.0,
        "avg_days_to_close": 57.7,
        "open_weighted_pipeline": 3065280.0
      },
      {
        "sales_rep": "Ethan Brown",
        "total_opportunities": 317,
        "won_deals": 67,
        "win_rate_pct": 28.6,
        "won_revenue": 3277300.0,
        "avg_days_to_close": 50.4,
        "open_weighted_pipeline": 1305005.0
      },
      {
        "sales_rep": "Noah Wilson",
        "total_opportunities": 311,
        "won_deals": 71,
        "win_rate_pct": 29.7,
        "won_revenue": 1868400.0,
        "avg_days_to_close": 42.0,
        "open_weighted_pipeline": 1471950.0
      }
    ],
    "source_performance": [
      {
        "lead_source": "Partner Referral",
        "total_opportunities": 426,
        "win_rate_pct": 43.4,
        "won_revenue": 11685900.0,
        "avg_won_deal_size": 89205.34
      },
      {
        "lead_source": "Inbound Demo",
        "total_opportunities": 431,
        "win_rate_pct": 37.3,
        "won_revenue": 11318100.0,
        "avg_won_deal_size": 99281.58
      },
      {
        "lead_source": "Customer Referral",
        "total_opportunities": 407,
        "win_rate_pct": 45.6,
        "won_revenue": 10511900.0,
        "avg_won_deal_size": 81487.6
      },
      {
        "lead_source": "Webinar",
        "total_opportunities": 464,
        "win_rate_pct": 31.7,
        "won_revenue": 10004200.0,
        "avg_won_deal_size": 95278.1
      },
      {
        "lead_source": "Paid Search",
        "total_opportunities": 427,
        "win_rate_pct": 24.4,
        "won_revenue": 7183500.0,
        "avg_won_deal_size": 95780.0
      },
      {
        "lead_source": "Outbound",
        "total_opportunities": 445,
        "win_rate_pct": 26.8,
        "won_revenue": 6886800.0,
        "avg_won_deal_size": 75679.12
      }
    ],
    "monthly_revenue": [
      {
        "month": "2024-02",
        "won_deals": 8,
        "won_revenue": 153900.0
      },
      {
        "month": "2024-03",
        "won_deals": 9,
        "won_revenue": 195100.0
      },
      {
        "month": "2024-04",
        "won_deals": 18,
        "won_revenue": 1284000.0
      },
      {
        "month": "2024-05",
        "won_deals": 19,
        "won_revenue": 1363700.0
      },
      {
        "month": "2024-06",
        "won_deals": 25,
        "won_revenue": 1778900.0
      },
      {
        "month": "2024-07",
        "won_deals": 27,
        "won_revenue": 2877500.0
      },
      {
        "month": "2024-08",
        "won_deals": 27,
        "won_revenue": 1988000.0
      },
      {
        "month": "2024-09",
        "won_deals": 22,
        "won_revenue": 1928600.0
      },
      {
        "month": "2024-10",
        "won_deals": 23,
        "won_revenue": 1612500.0
      },
      {
        "month": "2024-11",
        "won_deals": 15,
        "won_revenue": 1355900.0
      },
      {
        "month": "2024-12",
        "won_deals": 25,
        "won_revenue": 2249500.0
      },
      {
        "month": "2025-01",
        "won_deals": 32,
        "won_revenue": 2690300.0
      },
      {
        "month": "2025-02",
        "won_deals": 24,
        "won_revenue": 2484300.0
      },
      {
        "month": "2025-03",
        "won_deals": 24,
        "won_revenue": 2018400.0
      },
      {
        "month": "2025-04",
        "won_deals": 26,
        "won_revenue": 2026100.0
      },
      {
        "month": "2025-05",
        "won_deals": 25,
        "won_revenue": 2245600.0
      },
      {
        "month": "2025-06",
        "won_deals": 26,
        "won_revenue": 2050100.0
      },
      {
        "month": "2025-07",
        "won_deals": 23,
        "won_revenue": 2080700.0
      },
      {
        "month": "2025-08",
        "won_deals": 28,
        "won_revenue": 3082300.0
      },
      {
        "month": "2025-09",
        "won_deals": 21,
        "won_revenue": 2272600.0
      },
      {
        "month": "2025-10",
        "won_deals": 33,
        "won_revenue": 2803400.0
      },
      {
        "month": "2025-11",
        "won_deals": 27,
        "won_revenue": 2174500.0
      },
      {
        "month": "2025-12",
        "won_deals": 25,
        "won_revenue": 3359900.0
      },
      {
        "month": "2026-01",
        "won_deals": 33,
        "won_revenue": 4026300.0
      },
      {
        "month": "2026-02",
        "won_deals": 27,
        "won_revenue": 2825900.0
      },
      {
        "month": "2026-03",
        "won_deals": 31,
        "won_revenue": 3087400.0
      },
      {
        "month": "2026-04",
        "won_deals": 22,
        "won_revenue": 1575000.0
      }
    ],
    "pipeline_by_expected_month": [
      {
        "month": "2024-01",
        "open_opportunities": 1,
        "open_pipeline": 126300.0,
        "weighted_pipeline": 94725.0
      },
      {
        "month": "2024-02",
        "open_opportunities": 4,
        "open_pipeline": 36100.0,
        "weighted_pipeline": 23700.0
      },
      {
        "month": "2024-03",
        "open_opportunities": 11,
        "open_pipeline": 551800.0,
        "weighted_pipeline": 349600.0
      },
      {
        "month": "2024-04",
        "open_opportunities": 17,
        "open_pipeline": 948900.0,
        "weighted_pipeline": 535925.0
      },
      {
        "month": "2024-05",
        "open_opportunities": 18,
        "open_pipeline": 1367300.0,
        "weighted_pipeline": 783900.0
      },
      {
        "month": "2024-06",
        "open_opportunities": 23,
        "open_pipeline": 1835500.0,
        "weighted_pipeline": 1188275.0
      },
      {
        "month": "2024-07",
        "open_opportunities": 20,
        "open_pipeline": 1754400.0,
        "weighted_pipeline": 1158025.0
      },
      {
        "month": "2024-08",
        "open_opportunities": 26,
        "open_pipeline": 3465200.0,
        "weighted_pipeline": 2158025.0
      },
      {
        "month": "2024-09",
        "open_opportunities": 13,
        "open_pipeline": 1465900.0,
        "weighted_pipeline": 927725.0
      },
      {
        "month": "2024-10",
        "open_opportunities": 28,
        "open_pipeline": 2685300.0,
        "weighted_pipeline": 1693900.0
      },
      {
        "month": "2024-11",
        "open_opportunities": 22,
        "open_pipeline": 1359400.0,
        "weighted_pipeline": 859475.0
      },
      {
        "month": "2024-12",
        "open_opportunities": 24,
        "open_pipeline": 2285200.0,
        "weighted_pipeline": 1479300.0
      },
      {
        "month": "2025-01",
        "open_opportunities": 25,
        "open_pipeline": 2043600.0,
        "weighted_pipeline": 1291875.0
      },
      {
        "month": "2025-02",
        "open_opportunities": 20,
        "open_pipeline": 2077500.0,
        "weighted_pipeline": 1232075.0
      },
      {
        "month": "2025-03",
        "open_opportunities": 19,
        "open_pipeline": 2461700.0,
        "weighted_pipeline": 1598275.0
      },
      {
        "month": "2025-04",
        "open_opportunities": 22,
        "open_pipeline": 2515200.0,
        "weighted_pipeline": 1565850.0
      },
      {
        "month": "2025-05",
        "open_opportunities": 12,
        "open_pipeline": 897000.0,
        "weighted_pipeline": 595325.0
      },
      {
        "month": "2025-06",
        "open_opportunities": 25,
        "open_pipeline": 2360500.0,
        "weighted_pipeline": 1597000.0
      },
      {
        "month": "2025-07",
        "open_opportunities": 21,
        "open_pipeline": 1813900.0,
        "weighted_pipeline": 1200225.0
      },
      {
        "month": "2025-08",
        "open_opportunities": 20,
        "open_pipeline": 2321900.0,
        "weighted_pipeline": 1533425.0
      },
      {
        "month": "2025-09",
        "open_opportunities": 19,
        "open_pipeline": 1598100.0,
        "weighted_pipeline": 1077350.0
      },
      {
        "month": "2025-10",
        "open_opportunities": 25,
        "open_pipeline": 2523200.0,
        "weighted_pipeline": 1691425.0
      },
      {
        "month": "2025-11",
        "open_opportunities": 16,
        "open_pipeline": 1147700.0,
        "weighted_pipeline": 689425.0
      },
      {
        "month": "2025-12",
        "open_opportunities": 21,
        "open_pipeline": 1180200.0,
        "weighted_pipeline": 769325.0
      },
      {
        "month": "2026-01",
        "open_opportunities": 26,
        "open_pipeline": 2062400.0,
        "weighted_pipeline": 1357325.0
      },
      {
        "month": "2026-02",
        "open_opportunities": 20,
        "open_pipeline": 1922400.0,
        "weighted_pipeline": 1272975.0
      },
      {
        "month": "2026-03",
        "open_opportunities": 15,
        "open_pipeline": 1496200.0,
        "weighted_pipeline": 1080950.0
      },
      {
        "month": "2026-04",
        "open_opportunities": 27,
        "open_pipeline": 2091300.0,
        "weighted_pipeline": 1248450.0
      },
      {
        "month": "2026-05",
        "open_opportunities": 58,
        "open_pipeline": 6398400.0,
        "weighted_pipeline": 3228265.0
      },
      {
        "month": "2026-06",
        "open_opportunities": 49,
        "open_pipeline": 6233800.0,
        "weighted_pipeline": 3021515.0
      },
      {
        "month": "2026-07",
        "open_opportunities": 44,
        "open_pipeline": 8381000.0,
        "weighted_pipeline": 3365630.0
      },
      {
        "month": "2026-08",
        "open_opportunities": 23,
        "open_pipeline": 5101000.0,
        "weighted_pipeline": 1659840.0
      },
      {
        "month": "2026-09",
        "open_opportunities": 12,
        "open_pipeline": 2441600.0,
        "weighted_pipeline": 673505.0
      },
      {
        "month": "2026-10",
        "open_opportunities": 5,
        "open_pipeline": 1131100.0,
        "weighted_pipeline": 295190.0
      }
    ],
    "segment_performance": [
      {
        "account_segment": "Strategic",
        "total_opportunities": 584,
        "win_rate_pct": 31.4,
        "won_revenue": 30149000.0,
        "avg_won_deal_size": 251241.67,
        "avg_sales_cycle_days": 115.7
      },
      {
        "account_segment": "Enterprise",
        "total_opportunities": 666,
        "win_rate_pct": 36.8,
        "won_revenue": 18867900.0,
        "avg_won_deal_size": 104821.67,
        "avg_sales_cycle_days": 93.0
      },
      {
        "account_segment": "Mid-Market",
        "total_opportunities": 703,
        "win_rate_pct": 39.6,
        "won_revenue": 7221300.0,
        "avg_won_deal_size": 35572.91,
        "avg_sales_cycle_days": 53.9
      },
      {
        "account_segment": "SMB",
        "total_opportunities": 647,
        "win_rate_pct": 29.2,
        "won_revenue": 1352200.0,
        "avg_won_deal_size": 9522.54,
        "avg_sales_cycle_days": 34.8
      }
    ],
    "revenue_forecast": [
      {
        "month": "2026-05",
        "trend_forecast": 2962168.18,
        "weighted_pipeline": 3228265.0,
        "pipeline_adjusted_forecast": 3108521.43
      },
      {
        "month": "2026-06",
        "trend_forecast": 3012967.13,
        "weighted_pipeline": 3021515.0,
        "pipeline_adjusted_forecast": 3017668.46
      },
      {
        "month": "2026-07",
        "trend_forecast": 3063766.08,
        "weighted_pipeline": 3365630.0,
        "pipeline_adjusted_forecast": 3229791.24
      },
      {
        "month": "2026-08",
        "trend_forecast": 3114565.03,
        "weighted_pipeline": 1659840.0,
        "pipeline_adjusted_forecast": 2314466.26
      },
      {
        "month": "2026-09",
        "trend_forecast": 3165363.99,
        "weighted_pipeline": 673505.0,
        "pipeline_adjusted_forecast": 1794841.55
      },
      {
        "month": "2026-10",
        "trend_forecast": 3216162.94,
        "weighted_pipeline": 295190.0,
        "pipeline_adjusted_forecast": 1609627.82
      }
    ]
  },
  "recommendations": [
    "Prioritize Customer Referral and Partner Referral because they show the strongest conversion quality.",
    "Review late-stage pipeline coverage for Priya Shah; this rep owns the largest weighted open pipeline.",
    "Use the SMB sales motion as the fast-cycle benchmark and document what shortens deal velocity."
  ]
}
